harvest_sow-1.0.0b1.dist-info/DESCRIPTION.rst
harvest_sow-1.0.0b1.dist-info/entry_points.txt
harvest_sow-1.0.0b1.dist-info/METADATA
harvest_sow-1.0.0b1.dist-info/metadata.json
harvest_sow-1.0.0b1.dist-info/pbr.json
harvest_sow-1.0.0b1.dist-info/RECORD
harvest_sow-1.0.0b1.dist-info/top_level.txt
harvest_sow-1.0.0b1.dist-info/WHEEL
sow/__init__.py
sow/commands.py
sow/console.py
sow/utils.py
