Metadata-Version: 2.0
Name: harvest-sow
Version: 1.0.0b1
Summary: Harvest Command Line App
Home-page: http://www.github.com/mekhami/Sow
Author: Lawrence Vanderpool
Author-email: lawrence.vanderpool@gmail.com
License: MIT
Keywords: harvest sow api
Platform: UNKNOWN
Requires-Dist: docopt
Requires-Dist: keyring
Requires-Dist: python-harvest
